LICENSE
README.md
setup.cfg
setup.py
pymaxdb/__init__.py
pymaxdb/pymaxdb.py
pymaxdb.egg-info/PKG-INFO
pymaxdb.egg-info/SOURCES.txt
pymaxdb.egg-info/dependency_links.txt
pymaxdb.egg-info/requires.txt
pymaxdb.egg-info/top_level.txt