Metadata-Version: 2.1
Name: pymaxdb
Version: 1.1.4
Summary: Projeto que visa padronizar a comunicação com alguns bancos de dados
Home-page: https://github.com/ayronmax/pymaxdb
Author: Alexinaldo Costa
Author-email: ayronmax@gmail.com
License: MIT
Project-URL: Código fonte, https://github.com/ayronmax/pymaxdb
Project-URL: Download, https://github.com/ayronmax/pymaxdb/archive/master.zip
Keywords: ODBC PostgreSQL DBMaker Firebird SQLServer
Platform: UNKNOWN
Classifier: Development Status :: 5 - Production/Stable
Classifier: Intended Audience :: Developers
Classifier: License :: OSI Approved :: MIT License
Classifier: Natural Language :: Portuguese (Brazilian)
Classifier: Operating System :: OS Independent
Classifier: Topic :: Database
